pyexportvba/__init__.py
pyexportvba/__main__.py
pyexportvba/py.typed
pyexportvba/arguments/__init__.py
pyexportvba/arguments/arguments.py
pyexportvba/arguments/process_arguments.py
pyexportvba/arguments/py.typed
pyexportvba/export_vba/__init__.py
pyexportvba/export_vba/export_vba_from_excel_app.py
pyexportvba/export_vba/get_vb_comp_code.py
pyexportvba/export_vba/get_vb_comp_paths.py
pyexportvba/export_vba/py.typed
pyexportvba-0.0.3.dist-info/LICENSE
pyexportvba-0.0.3.dist-info/METADATA
pyexportvba-0.0.3.dist-info/WHEEL
pyexportvba-0.0.3.dist-info/entry_points.txt
pyexportvba-0.0.3.dist-info/top_level.txt
pyexportvba-0.0.3.dist-info/RECORD
