Metadata-Version: 2.1
Name: pyexportvba
Version: 0.0.3
Summary: A python package to export VBA code embedded in Excel files to separate BAS files
Author-email: Bassem Girgis <brgirgis@gmail.com>
Maintainer-email: Bassem Girgis <brgirgis@gmail.com>
License: MIT
Project-URL: Homepage, https://github.com/pyexportvba/pyexportvba
Project-URL: Documentation, https://github.com/pyexportvba/pyexportvba
Project-URL: Repository, https://github.com/pyexportvba/pyexportvba.git
Project-URL: Issues, https://github.com/pyexportvba/pyexportvba/issues
Keywords: VBA,export,Excel,Modules
Classifier: Development Status :: 5 - Production/Stable
Classifier: Environment :: Console
Classifier: Operating System :: Microsoft :: Windows
Classifier: License :: OSI Approved :: MIT License
Classifier: Programming Language :: Python :: 3.9
Classifier: Programming Language :: Python :: 3.10
Classifier: Programming Language :: Python :: 3.11
Classifier: Programming Language :: Python :: 3.12
Classifier: Programming Language :: Python :: 3.13
Requires-Python: >=3.9
License-File: LICENSE
Requires-Dist: pywin32
Provides-Extra: dev
Requires-Dist: build; extra == "dev"
Requires-Dist: flake8; extra == "dev"
Requires-Dist: mypy; extra == "dev"
Requires-Dist: pytest; extra == "dev"
Requires-Dist: twine; extra == "dev"
Requires-Dist: pylint; extra == "dev"
Requires-Dist: types-pywin32; extra == "dev"
